ocr_translate_easyocr/__init__.py
ocr_translate_easyocr/plugin.py
ocr_translate_easyocr-0.5.0.dist-info/entry_points.txt
ocr_translate_easyocr-0.5.0.dist-info/licenses/LICENSE.txt
ocr_translate_easyocr-0.5.0.dist-info/WHEEL
ocr_translate_easyocr-0.5.0.dist-info/METADATA
ocr_translate_easyocr-0.5.0.dist-info/RECORD
