Metadata-Version: 2.4
Name: ocr_translate-easyocr
Version: 0.5.0
Summary: Plugins to enable usage of Easyocr in ocr_translate
Keywords: django,translation
Requires-Python: >=3.10
Classifier: Programming Language :: Python
Classifier: Programming Language :: Python :: 3.10
Classifier: Programming Language :: Python :: 3.11
Classifier: Programming Language :: Python :: 3.12
Classifier: Programming Language :: Python :: 3.13
License-File: LICENSE.txt
Requires-Dist: django-ocr_translate>=0.7.0,<1.0
Requires-Dist: torch~=2.8.0
Requires-Dist: torchvision~=0.23.0
Requires-Dist: scipy~=1.15.3
Requires-Dist: easyocr~=1.7.2
Requires-Dist: pre-commit ; extra == "pre-commit"
Requires-Dist: pylint ; extra == "pre-commit"
Requires-Dist: pylint-pytest ; extra == "pre-commit"
Requires-Dist: pylint-django ; extra == "pre-commit"
Requires-Dist: flit ; extra == "release"
Requires-Dist: pytest ; extra == "tests"
Requires-Dist: pytest-cov ; extra == "tests"
Requires-Dist: pytest-regressions ; extra == "tests"
Requires-Dist: pytest-django ; extra == "tests"
Project-URL: Source, https://github.com/Crivella/ocr_translate-easyocr
Provides-Extra: pre-commit
Provides-Extra: release
Provides-Extra: tests
